{
  "success": true,
  "creationTimestamp": 1759927428,
  "elements": [
    {
      "id": "Q1",
      "type": "QUESTION",
      "items": [
        {
          "itemType": "TEXT",
          "content": "Reken uit."
        },
        {
          "itemType": "TEXT",
          "content": "$\\frac{2}{9} : 2$"
        },
        {
          "id": "fiI08",
          "itemType": "INTERACTION",
          "interactionType": "MULTISTEP",
          "result": {
            "status": "FINISHED",
            "progress": 1,
            "events": [
              {
                "timestamp": 1759927432390,
                "event": "EVALUATE",
                "tags": [],
                "annotations": [
                  {
                    "type": "ERROR_FEEDBACK",
                    "content": "Rekenfout:  $\\frac{2}{9} : 2$  is niet gelijk aan  $\\frac{1}{18}$ .",
                    "expression": "$\\begingroup\\color{darkred}\\begingroup \\frac{1}{18}\\endgroup\\endgroup$"
                  },
                  {
                    "type": "INPUT",
                    "content": "$\\frac{1}{18}$"
                  }
                ],
                "exerciseStatus": "ERROR",
                "progress": 0,
                "inputStatus": "ERROR"
              },
              {
                "timestamp": 1759927444115,
                "event": "EVALUATE",
                "tags": [],
                "annotations": [
                  {
                    "type": "ERROR_FEEDBACK",
                    "content": "Rekenfout:  $\\frac{2}{9} : 2$  is niet gelijk aan  $\\frac{12}{18}$ .",
                    "expression": "$\\begingroup\\color{darkred}\\begingroup \\frac{12}{18}\\endgroup\\endgroup$"
                  },
                  {
                    "type": "INPUT",
                    "content": "$\\frac{12}{18}$"
                  }
                ],
                "exerciseStatus": "ERROR",
                "progress": 0,
                "inputStatus": "ERROR"
              },
              {
                "timestamp": 1759927449150,
                "event": "EVALUATE",
                "tags": [
                  {
                    "id": "FractionArithmeticSimplifyProper",
                    "source": "NEXT_STEP"
                  }
                ],
                "annotations": [
                  {
                    "type": "INPUT",
                    "content": "$\\frac{2}{18}$"
                  }
                ],
                "exerciseStatus": "CORRECT",
                "progress": 0,
                "inputStatus": "CORRECT",
                "skillsTodo": [
                  "FractionArithmeticSimplifyProper"
                ]
              },
              {
                "timestamp": 1759927451925,
                "event": "EVALUATE",
                "tags": [
                  {
                    "id": "FractionArithmeticDivisionProperByNumber",
                    "source": "FINISHED_STEP"
                  },
                  {
                    "id": "FractionArithmeticSimplifyProper",
                    "source": "FINISHED_STEP"
                  }
                ],
                "annotations": [
                  {
                    "type": "INPUT",
                    "content": "$\\frac{1}{9}$"
                  }
                ],
                "exerciseStatus": "FINISHED",
                "progress": 1,
                "inputStatus": "FINISHED"
              }
            ],
            "tags": [
              {
                "id": "FractionArithmeticDivisionProperByNumber",
                "source": "FINISHED_STEP"
              },
              {
                "id": "FractionArithmeticSimplifyProper",
                "source": "FINISHED_STEP"
              }
            ],
            "scoring": {
              "marksEarned": 1,
              "marksTotal": 1,
              "penalties": {
                "marksPenalty": 0,
                "hintsRequested": 0,
                "mathErrors": 2
              },
              "finished": true
            }
          },
          "solution": "$\\frac{1}{9}$",
          "derivation": [
            {
              "expression": "$\\frac{2}{9} : 2$"
            },
            {
              "result": "$\\frac{2}{2\\cdot 9}$",
              "skills": [
                "FractionArithmeticDivisionProperByNumber"
              ],
              "description": "Vereenvoudig de breuk"
            },
            {
              "result": "$\\frac{1}{9}$",
              "skills": [
                "FractionArithmeticSimplifyProper"
              ],
              "description": "Deel de gemeenschappelijke factor weg uit teller en noemer"
            }
          ]
        }
      ]
    }
  ],
  "tagDescriptions": {
    "FractionArithmeticDivisionProperByNumber": {
      "descr": {
        "nl": "Een echte breuk delen door een getal"
      },
      "stepType": "CALCULATE"
    },
    "FractionArithmeticSimplifyProper": {
      "descr": {
        "nl": "Een breuk vereenvoudigen"
      },
      "stepType": "CALCULATE"
    }
  },
  "scoring": {
    "finished": true,
    "marksEarned": 1,
    "marksTotal": 1,
    "penalties": {
      "hintsRequested": 0,
      "mathErrors": 2,
      "marksPenalty": 0
    }
  }
}