{
  "success": true,
  "creationTimestamp": 1748629630,
  "elements": [
    {
      "id": "Q1",
      "type": "QUESTION",
      "items": [
        {
          "itemType": "TEXT",
          "content": "Reken uit."
        },
        {
          "itemType": "TEXT",
          "content": "$\\frac{1}{3} : 8$"
        },
        {
          "id": "fiI08",
          "itemType": "INTERACTION",
          "interactionType": "MULTISTEP",
          "result": {
            "status": "ERROR",
            "progress": 0,
            "events": [
              {
                "timestamp": 1748629717496,
                "event": "EVALUATE",
                "tags": [],
                "annotations": [
                  {
                    "type": "ERROR_FEEDBACK",
                    "content": "Rekenfout:  $\\frac{1}{3} : 8$  is niet gelijk aan  $\\frac{8}{3}$ .",
                    "expression": "$\\begingroup\\color{darkred}\\begingroup \\frac{8}{3}\\endgroup\\endgroup$"
                  },
                  {
                    "type": "INPUT",
                    "content": "$\\frac{8}{3}$"
                  }
                ],
                "exerciseStatus": "ERROR",
                "progress": 0,
                "inputStatus": "ERROR"
              },
              {
                "timestamp": 1748629725581,
                "event": "EVALUATE",
                "tags": [],
                "annotations": [
                  {
                    "type": "ERROR_FEEDBACK",
                    "content": "Rekenfout:  $\\frac{1}{3} : 8$  is niet gelijk aan  $\\frac{8}{1}$ .",
                    "expression": "$\\begingroup\\color{darkred}\\begingroup \\frac{8}{1}\\endgroup\\endgroup$"
                  },
                  {
                    "type": "INPUT",
                    "content": "$\\frac{8}{1}$"
                  }
                ],
                "exerciseStatus": "ERROR",
                "progress": 0,
                "inputStatus": "ERROR"
              },
              {
                "timestamp": 1748629741899,
                "event": "EVALUATE",
                "tags": [],
                "annotations": [
                  {
                    "type": "ERROR_FEEDBACK",
                    "content": "Je ben factor  $3$  vergeten uit de noemer.",
                    "expression": "$\\frac{1}{8}$"
                  },
                  {
                    "type": "INPUT",
                    "content": "$\\frac{1}{8}$"
                  }
                ],
                "exerciseStatus": "ERROR",
                "progress": 0,
                "inputStatus": "ERROR"
              }
            ],
            "tags": [],
            "scoring": {
              "marksEarned": 0,
              "marksTotal": 1,
              "penalties": {
                "marksPenalty": 0,
                "hintsRequested": 0,
                "mathErrors": 3
              },
              "finished": false
            }
          },
          "solution": "$\\frac{1}{24}$",
          "derivation": [
            {
              "expression": "$\\frac{1}{3} : 8$"
            },
            {
              "result": "$\\frac{1}{24}$",
              "skills": [
                "FractionArithmeticDivisionProperByNumber"
              ],
              "description": "Vereenvoudig de breuk"
            }
          ]
        }
      ]
    }
  ],
  "tagDescriptions": {
    "FractionArithmeticDivisionProperByNumber": {
      "descr": {
        "nl": "Een echte breuk delen door een getal"
      },
      "stepType": "CALCULATE"
    }
  },
  "scoring": {
    "finished": false,
    "marksEarned": 0,
    "marksTotal": 1,
    "penalties": {
      "hintsRequested": 0,
      "mathErrors": 3,
      "marksPenalty": 0
    }
  }
}