{
  "success": true,
  "creationTimestamp": 1747828863,
  "elements": [
    {
      "id": "Q1",
      "type": "QUESTION",
      "items": [
        {
          "itemType": "TEXT",
          "content": "Los de vergelijking op."
        },
        {
          "itemType": "TEXT",
          "content": "$3 s ^{2}=108$"
        },
        {
          "id": "ybGQg",
          "itemType": "INTERACTION",
          "interactionType": "MULTISTEP",
          "result": {
            "status": "FINISHED",
            "progress": 1,
            "events": [
              {
                "timestamp": 1747828882336,
                "event": "EVALUATE",
                "tags": [],
                "annotations": [
                  {
                    "type": "INPUT",
                    "content": "$3s^{2}-108=0$"
                  }
                ],
                "exerciseStatus": "CORRECT",
                "progress": 0,
                "inputStatus": "CORRECT",
                "skillsTodo": [
                  "EquationsBalanceMethodArrangeTerms",
                  "EquationsOperationsAdd",
                  "EquationsBalanceMethodDivideCoefficient",
                  "EquationsOperationsMultiply"
                ]
              },
              {
                "timestamp": 1747828911228,
                "event": "EVALUATE",
                "tags": [],
                "annotations": [
                  {
                    "type": "ERROR_FEEDBACK",
                    "content": "Je hebt de balansmethode niet goed toegepast.",
                    "expression": "$\\begingroup\\color{darkred}\\begingroup 3 s ^{2}=36\\endgroup\\endgroup$"
                  },
                  {
                    "type": "INPUT",
                    "content": "$3s^{2}=36$"
                  }
                ],
                "exerciseStatus": "ERROR",
                "progress": 0,
                "inputStatus": "ERROR"
              },
              {
                "timestamp": 1747828937019,
                "event": "EVALUATE",
                "tags": [],
                "annotations": [
                  {
                    "type": "INPUT",
                    "content": "$3s^{2}=108$"
                  }
                ],
                "exerciseStatus": "CORRECT",
                "progress": 0,
                "inputStatus": "CORRECT",
                "skillsTodo": [
                  "EquationsBalanceMethodDivideCoefficient",
                  "EquationsOperationsMultiply"
                ]
              },
              {
                "timestamp": 1747828960904,
                "event": "EVALUATE",
                "tags": [],
                "annotations": [
                  {
                    "type": "INPUT",
                    "content": "$3s^{2}-108=0$"
                  }
                ],
                "exerciseStatus": "CORRECT",
                "progress": 0,
                "inputStatus": "CORRECT",
                "skillsTodo": [
                  "EquationsBalanceMethodArrangeTerms",
                  "EquationsOperationsAdd",
                  "EquationsBalanceMethodDivideCoefficient",
                  "EquationsOperationsMultiply"
                ]
              },
              {
                "timestamp": 1747828971298,
                "event": "HINT",
                "tags": [
                  {
                    "id": "EquationsBalanceMethodArrangeTerms",
                    "weight": 100,
                    "source": "HINT"
                  },
                  {
                    "id": "EquationsOperationsAdd",
                    "weight": 100,
                    "source": "HINT"
                  }
                ],
                "annotations": [
                  {
                    "type": "HINT",
                    "content": "Balansmethode: Tel links en rechts  $108$  erbij op.",
                    "expression": "$3 s ^{2}- \\begingroup\\color{#336699}\\begingroup 108\\endgroup\\endgroup=\\begingroup\\color{#336699}\\begingroup 0\\endgroup\\endgroup$"
                  }
                ]
              },
              {
                "timestamp": 1747828980117,
                "event": "EVALUATE",
                "tags": [],
                "annotations": [
                  {
                    "type": "INPUT",
                    "content": "$3s^{2}=108$"
                  }
                ],
                "exerciseStatus": "CORRECT",
                "progress": 0,
                "inputStatus": "CORRECT",
                "skillsTodo": [
                  "EquationsBalanceMethodDivideCoefficient",
                  "EquationsOperationsMultiply"
                ]
              },
              {
                "timestamp": 1747828992607,
                "event": "EVALUATE",
                "tags": [],
                "annotations": [
                  {
                    "type": "INPUT",
                    "content": "$108:3=36$"
                  }
                ],
                "exerciseStatus": "CORRECT",
                "progress": 0,
                "inputStatus": "TRUE_EXPRESSION"
              },
              {
                "timestamp": 1747829011021,
                "event": "EVALUATE",
                "tags": [],
                "annotations": [
                  {
                    "type": "INPUT",
                    "content": "$s^{2}=36$"
                  }
                ],
                "exerciseStatus": "CORRECT",
                "progress": 0,
                "inputStatus": "CORRECT"
              },
              {
                "timestamp": 1747829019975,
                "event": "EVALUATE",
                "tags": [
                  {
                    "id": "EquationsOperationsPower",
                    "weight": -100,
                    "errors": [
                      "MissingSolutions"
                    ]
                  }
                ],
                "annotations": [
                  {
                    "type": "ERROR_FEEDBACK",
                    "content": "<h1>Hoeveel oplossingen verwacht je?</h1>Als  $t ^{2}=c $ , met  $c > 0$ ,  dan geldt  $t =\\sqrt{c }\\vee t =\\text{-}\\sqrt{c }$ .",
                    "expression": "$\\begingroup\\color{darkred}\\begingroup s =6\\endgroup\\endgroup$"
                  },
                  {
                    "type": "INPUT",
                    "content": "$s=6$"
                  }
                ],
                "exerciseStatus": "ERROR",
                "progress": 0,
                "inputStatus": "ERROR"
              },
              {
                "timestamp": 1747829035108,
                "event": "EVALUATE",
                "tags": [
                  {
                    "id": "EquationsBalanceMethodDivideCoefficient",
                    "weight": 100
                  },
                  {
                    "id": "EquationsOperationsMultiply",
                    "weight": 100
                  }
                ],
                "annotations": [
                  {
                    "type": "INPUT",
                    "content": "$s=6\\ of\\ s=-6$"
                  }
                ],
                "exerciseStatus": "FINISHED",
                "progress": 1,
                "inputStatus": "FINISHED"
              }
            ],
            "tags": [
              {
                "id": "EquationsBalanceMethodArrangeTerms",
                "weight": 100,
                "source": "HINT"
              },
              {
                "id": "EquationsOperationsAdd",
                "weight": 100,
                "source": "HINT"
              },
              {
                "id": "EquationsOperationsPower",
                "weight": -100,
                "errors": [
                  "MissingSolutions"
                ]
              },
              {
                "id": "EquationsBalanceMethodDivideCoefficient",
                "weight": 100
              },
              {
                "id": "EquationsOperationsMultiply",
                "weight": 100
              }
            ],
            "scoring": {
              "marksEarned": 1,
              "marksTotal": 1,
              "penalties": {
                "marksPenalty": 0,
                "hintsRequested": 1,
                "mathErrors": 2
              },
              "finished": true
            }
          },
          "solution": "$s =\\text{-}6\\vee s =6$",
          "derivation": [
            {
              "expression": "$3 s ^{2}=108$"
            },
            {
              "result": "$s ^{2}=36$",
              "skills": [
                "EquationsBalanceMethodDivideCoefficient",
                "EquationsOperationsMultiply"
              ],
              "description": "Deel links en rechts door  $3$"
            },
            {
              "result": "$s =\\sqrt{36}\\vee s =\\text{-}\\sqrt{36}$",
              "description": "Herleid de vergelijking door links en rechts de wortel te nemen"
            },
            {
              "result": "$s =\\text{-}6\\vee s =6$",
              "description": "Bepaal de wortel van  $36$"
            }
          ]
        }
      ]
    }
  ],
  "tagDescriptions": {
    "EquationsBalanceMethodDivideCoefficient": {
      "descr": {
        "nl": "Delen door de coëfficiënt voor de variabele om de oplossing te krijgen."
      },
      "stepType": "STRATEGY"
    },
    "EquationsOperationsMultiply": {
      "descr": {
        "nl": "Vermenigvuldigen of delen van een vergelijking via de balansmethode"
      },
      "stepType": "STRATEGY"
    },
    "EquationsBalanceMethodArrangeTerms": {
      "descr": {
        "nl": "Termen met de variabele naar links en andere termen naar rechts halen."
      },
      "stepType": "STRATEGY"
    },
    "EquationsOperationsAdd": {
      "descr": {
        "nl": "Termen optellen of aftrekken via de balansmethode"
      },
      "stepType": "STRATEGY"
    },
    "EquationsOperationsPower": {
      "descr": {
        "nl": "Een macht toepassen op een vergelijking"
      },
      "stepType": "STRATEGY",
      "errors": [
        {
          "id": "MissingSolutions",
          "type": [
            "MISCONCEPTION"
          ],
          "descr": {
            "nl": "Zich niet realiseren dat er meerdere oplossingen zijn van de machtsvergelijking."
          }
        }
      ]
    }
  },
  "scoring": {
    "finished": true,
    "marksEarned": 1,
    "marksTotal": 1,
    "penalties": {
      "hintsRequested": 1,
      "mathErrors": 2,
      "marksPenalty": 0
    }
  }
}