{
  "success": true,
  "creationTimestamp": 1747765747,
  "elements": [
    {
      "id": "Q1",
      "type": "QUESTION",
      "items": [
        {
          "itemType": "TEXT",
          "content": "Los de vergelijking op."
        },
        {
          "itemType": "TEXT",
          "content": "$133=n ^{2}- 63$"
        },
        {
          "id": "IQVCv",
          "itemType": "INTERACTION",
          "interactionType": "MULTISTEP",
          "result": {
            "status": "FINISHED",
            "progress": 1,
            "events": [
              {
                "timestamp": 1747765793554,
                "event": "EVALUATE",
                "tags": [
                  {
                    "id": "EquationsOperationsAdd",
                    "weight": -100,
                    "errors": [
                      "AddSubtract"
                    ]
                  }
                ],
                "annotations": [
                  {
                    "type": "ERROR_FEEDBACK",
                    "content": "<h1>Je hebt de balansmethode niet goed toegepast.</h1>Je hebt aan de ene zijde  $133$  opgeteld, maar aan de andere zijde  $133$  afgetrokken.",
                    "expression": "$\\begingroup\\color{darkred}\\begingroup n ^{2}- 63+ 133=0\\endgroup\\endgroup$"
                  },
                  {
                    "type": "INPUT",
                    "content": "$n^{2}-63+133=0$"
                  }
                ],
                "exerciseStatus": "ERROR",
                "progress": 0,
                "inputStatus": "ERROR"
              },
              {
                "timestamp": 1747765829183,
                "event": "EVALUATE",
                "tags": [
                  {
                    "id": "NumberArithmeticAddConcept",
                    "weight": -100
                  }
                ],
                "annotations": [
                  {
                    "type": "ERROR_FEEDBACK",
                    "content": "Je hebt de balansmethode niet goed toegepast.",
                    "expression": "$\\begingroup\\color{darkred}\\begingroup n ^{2}- 70=0\\endgroup\\endgroup$"
                  },
                  {
                    "type": "INPUT",
                    "content": "$n^{2}-70=0$"
                  }
                ],
                "exerciseStatus": "ERROR",
                "progress": 0,
                "inputStatus": "ERROR"
              },
              {
                "timestamp": 1747765862049,
                "event": "EVALUATE",
                "tags": [],
                "annotations": [
                  {
                    "type": "INPUT",
                    "content": "$n^{2}-196=0$"
                  }
                ],
                "exerciseStatus": "CORRECT",
                "progress": 0,
                "inputStatus": "CORRECT",
                "skillsTodo": [
                  "EquationsBalanceMethodArrangeTerms",
                  "EquationsOperationsAdd"
                ]
              },
              {
                "timestamp": 1747765973670,
                "event": "EVALUATE",
                "tags": [],
                "annotations": [
                  {
                    "type": "INPUT",
                    "content": "$n^{2}=196$"
                  }
                ],
                "exerciseStatus": "CORRECT",
                "progress": 0,
                "inputStatus": "CORRECT"
              },
              {
                "timestamp": 1747766015250,
                "event": "EVALUATE",
                "tags": [
                  {
                    "id": "EquationsOperationsPower",
                    "weight": -100,
                    "errors": [
                      "MissingSolutions"
                    ]
                  }
                ],
                "annotations": [
                  {
                    "type": "ERROR_FEEDBACK",
                    "content": "<h1>Hoeveel oplossingen verwacht je?</h1>Als  $t ^{2}=c $ , met  $c > 0$ ,  dan geldt  $t =\\sqrt{c }\\vee t =\\text{-}\\sqrt{c }$ .",
                    "expression": "$\\begingroup\\color{darkred}\\begingroup n =14\\endgroup\\endgroup$"
                  },
                  {
                    "type": "INPUT",
                    "content": "$n=14$"
                  }
                ],
                "exerciseStatus": "ERROR",
                "progress": 0,
                "inputStatus": "ERROR"
              },
              {
                "timestamp": 1747766026334,
                "event": "EVALUATE",
                "tags": [
                  {
                    "id": "EquationsBalanceMethodArrangeTerms",
                    "weight": 100
                  },
                  {
                    "id": "EquationsOperationsAdd",
                    "weight": 100
                  }
                ],
                "annotations": [
                  {
                    "type": "INPUT",
                    "content": "$n=14\\ v\\ n=-14$"
                  }
                ],
                "exerciseStatus": "FINISHED",
                "progress": 1,
                "inputStatus": "FINISHED"
              }
            ],
            "tags": [
              {
                "id": "EquationsOperationsAdd",
                "weight": -100,
                "errors": [
                  "AddSubtract"
                ]
              },
              {
                "id": "NumberArithmeticAddConcept",
                "weight": -100
              },
              {
                "id": "EquationsOperationsPower",
                "weight": -100,
                "errors": [
                  "MissingSolutions"
                ]
              },
              {
                "id": "EquationsBalanceMethodArrangeTerms",
                "weight": 100
              },
              {
                "id": "EquationsOperationsAdd",
                "weight": 100
              }
            ],
            "scoring": {
              "marksEarned": 1,
              "marksTotal": 1,
              "penalties": {
                "marksPenalty": 0,
                "hintsRequested": 0,
                "mathErrors": 3
              },
              "finished": true
            }
          },
          "solution": "$n =\\text{-}14\\vee n =14$",
          "derivation": [
            {
              "expression": "$133=n ^{2}- 63$"
            },
            {
              "result": "$196=n ^{2}$",
              "skills": [
                "EquationsBalanceMethodArrangeTerms",
                "EquationsOperationsAdd"
              ],
              "description": "Balansmethode: Tel links en rechts  $63$  erbij op."
            },
            {
              "result": "$n =\\sqrt{196}\\vee n =\\text{-}\\sqrt{196}$",
              "description": "Herleid de vergelijking door links en rechts de wortel te nemen"
            },
            {
              "result": "$n =\\text{-}14\\vee n =14$",
              "description": "Bepaal de wortel van  $196$"
            }
          ]
        }
      ]
    }
  ],
  "tagDescriptions": {
    "EquationsBalanceMethodArrangeTerms": {
      "descr": {
        "nl": "Termen met de variabele naar links en andere termen naar rechts halen."
      },
      "stepType": "STRATEGY"
    },
    "EquationsOperationsAdd": {
      "descr": {
        "nl": "Termen optellen of aftrekken via de balansmethode"
      },
      "stepType": "STRATEGY",
      "errors": [
        {
          "id": "AddSubtract",
          "type": [
            "MISCONCEPTION"
          ],
          "descr": {
            "nl": "Optellen aan één kant en aftrekken aan de andere kant van de vergelijking."
          }
        }
      ]
    },
    "NumberArithmeticAddConcept": {
      "descr": {
        "nl": "Optellen en aftrekken begrijpen"
      },
      "stepType": "CONCEPT"
    },
    "EquationsOperationsPower": {
      "descr": {
        "nl": "Een macht toepassen op een vergelijking"
      },
      "stepType": "STRATEGY",
      "errors": [
        {
          "id": "MissingSolutions",
          "type": [
            "MISCONCEPTION"
          ],
          "descr": {
            "nl": "Zich niet realiseren dat er meerdere oplossingen zijn van de machtsvergelijking."
          }
        }
      ]
    }
  },
  "scoring": {
    "finished": true,
    "marksEarned": 1,
    "marksTotal": 1,
    "penalties": {
      "hintsRequested": 0,
      "mathErrors": 3,
      "marksPenalty": 0
    }
  }
}