{
  "success": true,
  "creationTimestamp": 1742810833,
  "elements": [
    {
      "id": "Q1",
      "type": "QUESTION",
      "items": [
        {
          "itemType": "TEXT",
          "content": "Solve the equation."
        },
        {
          "itemType": "TEXT",
          "content": "$\\frac{3}{16}=\\frac{a }{16}$"
        },
        {
          "id": "aiFhh",
          "itemType": "INTERACTION",
          "interactionType": "MULTISTEP",
          "result": {
            "status": "FINISHED",
            "progress": 1,
            "events": [
              {
                "timestamp": 1742810861119,
                "event": "EVALUATE",
                "tags": [],
                "annotations": [
                  {
                    "type": "INPUT",
                    "content": "$a=3$"
                  }
                ],
                "exerciseStatus": "FINISHED",
                "progress": 1,
                "inputStatus": "FINISHED"
              }
            ],
            "tags": [],
            "scoring": {
              "marksEarned": 1,
              "marksTotal": 1,
              "penalties": {
                "marksPenalty": 0,
                "hintsRequested": 0,
                "mathErrors": 0
              },
              "finished": true
            }
          },
          "solution": "$a =3$",
          "derivation": [
            {
              "expression": "$\\frac{3}{16}=\\frac{a }{16}$"
            },
            {
              "result": "$a =3$",
              "description": "Multiply both sides by  $16$"
            }
          ]
        }
      ]
    }
  ],
  "tagDescriptions": {},
  "scoring": {
    "finished": true,
    "marksEarned": 1,
    "marksTotal": 1,
    "penalties": {
      "hintsRequested": 0,
      "mathErrors": 0,
      "marksPenalty": 0
    }
  }
}