{
  "success": true,
  "creationTimestamp": 1743333726,
  "elements": [
    {
      "id": "Q1",
      "type": "QUESTION",
      "items": [
        {
          "itemType": "TEXT",
          "content": "Vereenvoudig."
        },
        {
          "itemType": "TEXT",
          "content": "$\\sqrt{224}$"
        },
        {
          "id": "rJQ8D",
          "itemType": "INTERACTION",
          "interactionType": "MULTISTEP",
          "result": {
            "status": "FINISHED",
            "progress": 1,
            "events": [
              {
                "timestamp": 1743333736630,
                "event": "EVALUATE",
                "tags": [
                  {
                    "id": "AlgebraProductOfRoots",
                    "weight": -50
                  }
                ],
                "annotations": [
                  {
                    "type": "ERROR_FEEDBACK",
                    "content": "$\\sqrt{2} \\sqrt{122}$  is niet gelijk aan  $\\sqrt{224}$ .",
                    "expression": "$\\begingroup\\color{darkred}\\begingroup \\sqrt{122} \\sqrt{2}\\endgroup\\endgroup$"
                  },
                  {
                    "type": "INPUT",
                    "content": "$\\sqrt{122}\\sqrt{2}$"
                  }
                ],
                "exerciseStatus": "ERROR",
                "progress": 0,
                "inputStatus": "ERROR"
              },
              {
                "timestamp": 1743333782096,
                "event": "EVALUATE",
                "tags": [],
                "annotations": [
                  {
                    "type": "INPUT",
                    "content": "$\\sqrt{56}\\sqrt{4}$"
                  }
                ],
                "exerciseStatus": "CORRECT",
                "progress": 0,
                "inputStatus": "CORRECT"
              },
              {
                "timestamp": 1743333804343,
                "event": "EVALUATE",
                "tags": [],
                "annotations": [
                  {
                    "type": "INPUT",
                    "content": "$\\sqrt{28}\\sqrt{8}$"
                  }
                ],
                "exerciseStatus": "CORRECT",
                "progress": 0,
                "inputStatus": "CORRECT"
              },
              {
                "timestamp": 1743333817393,
                "event": "EVALUATE",
                "tags": [],
                "annotations": [
                  {
                    "type": "INPUT",
                    "content": "$\\sqrt{14}\\sqrt{16}$"
                  }
                ],
                "exerciseStatus": "CORRECT",
                "progress": 0,
                "inputStatus": "CORRECT"
              },
              {
                "timestamp": 1743333823314,
                "event": "EVALUATE",
                "tags": [],
                "annotations": [
                  {
                    "type": "INPUT",
                    "content": "$4\\sqrt{14}$"
                  }
                ],
                "exerciseStatus": "FINISHED",
                "progress": 1,
                "inputStatus": "FINISHED"
              }
            ],
            "tags": [
              {
                "id": "AlgebraProductOfRoots",
                "weight": -50
              }
            ],
            "scoring": {
              "marksEarned": 1,
              "marksTotal": 1,
              "penalties": {
                "marksPenalty": 0,
                "hintsRequested": 0,
                "mathErrors": 1
              },
              "finished": true
            }
          },
          "solution": "$4 \\sqrt{14}$",
          "derivation": [
            {
              "expression": "$\\sqrt{224}$"
            },
            {
              "result": "$\\sqrt{16} \\sqrt{14}$",
              "description": "Vereenvoudig de wortel"
            },
            {
              "result": "$4 \\sqrt{14}$",
              "description": "Bepaal de wortel van  $16$"
            }
          ]
        }
      ]
    }
  ],
  "tagDescriptions": {
    "AlgebraProductOfRoots": {
      "descr": {
        "nl": "De regels voor vermenigvuldigen van wortels toepassen"
      },
      "stepType": "ALGEBRA"
    }
  },
  "scoring": {
    "finished": true,
    "marksEarned": 1,
    "marksTotal": 1,
    "penalties": {
      "hintsRequested": 0,
      "mathErrors": 1,
      "marksPenalty": 0
    }
  }
}