{
  "success": true,
  "creationTimestamp": 1730731520,
  "elements": [
    {
      "id": "Q1",
      "type": "QUESTION",
      "items": [
        {
          "itemType": "TEXT",
          "content": "Bereken en vereenvoudig."
        },
        {
          "itemType": "TEXT",
          "content": "$\\text{-}280 : \\text{-}10$"
        },
        {
          "id": "YSQiy",
          "itemType": "INTERACTION",
          "interactionType": "MULTISTEP",
          "result": {
            "status": "FINISHED",
            "progress": 1,
            "events": [
              {
                "timestamp": 1730731790687,
                "event": "HINT",
                "tags": [],
                "annotations": [
                  {
                    "type": "HINT",
                    "content": "Bereken de deling",
                    "expression": "$\\text{-}280 : \\text{-}10$"
                  }
                ]
              },
              {
                "timestamp": 1730731846840,
                "event": "EVALUATE",
                "tags": [],
                "annotations": [
                  {
                    "type": "INPUT",
                    "content": "$-280:-10=28$"
                  }
                ],
                "exerciseStatus": "FINISHED",
                "progress": 1,
                "inputStatus": "FINISHED"
              }
            ],
            "tags": [],
            "scoring": {
              "marksEarned": 1,
              "marksTotal": 1,
              "penalties": {
                "marksPenalty": 0,
                "hintsRequested": 1,
                "mathErrors": 0
              },
              "finished": true
            }
          },
          "solution": "$28$",
          "derivation": [
            {
              "expression": "$\\text{-}280 : \\text{-}10$"
            },
            {
              "result": "$28$",
              "description": "Reken uit:  $\\text{-}280 : \\text{-}10$"
            }
          ]
        }
      ]
    }
  ],
  "tagDescriptions": {},
  "scoring": {
    "finished": true,
    "marksEarned": 1,
    "marksTotal": 1,
    "penalties": {
      "hintsRequested": 1,
      "mathErrors": 0,
      "marksPenalty": 0
    }
  }
}