{
  "success": true,
  "creationTimestamp": 1730747848,
  "elements": [
    {
      "id": "Q1",
      "type": "QUESTION",
      "items": [
        {
          "itemType": "TEXT",
          "content": "<strong>Calculate  $42+ 24+ 58$ .</strong>"
        },
        {
          "id": "GtWCQ",
          "itemType": "INTERACTION",
          "interactionType": "ARITHMETIC",
          "result": {
            "status": "FINISHED",
            "progress": 1,
            "events": [
              {
                "timestamp": 1730747848236,
                "event": "EVALUATE",
                "tags": [],
                "annotations": [],
                "exerciseStatus": "UNKNOWN",
                "progress": 0.03125
              },
              {
                "timestamp": 1730747853147,
                "event": "EVALUATE",
                "tags": [],
                "annotations": [],
                "exerciseStatus": "UNKNOWN",
                "progress": 0.09375
              },
              {
                "timestamp": 1730747856567,
                "event": "EVALUATE",
                "tags": [],
                "annotations": [],
                "exerciseStatus": "UNKNOWN",
                "progress": 0.15625
              },
              {
                "timestamp": 1730747861151,
                "event": "EVALUATE",
                "tags": [],
                "annotations": [],
                "exerciseStatus": "UNKNOWN",
                "progress": 0.1875
              },
              {
                "timestamp": 1730747862316,
                "event": "EVALUATE",
                "tags": [],
                "annotations": [],
                "exerciseStatus": "UNKNOWN",
                "progress": 0.25
              },
              {
                "timestamp": 1730747869826,
                "event": "EVALUATE",
                "tags": [],
                "annotations": [],
                "exerciseStatus": "UNKNOWN",
                "progress": 0.625
              },
              {
                "timestamp": 1730747875554,
                "event": "EVALUATE",
                "tags": [],
                "annotations": [],
                "exerciseStatus": "UNKNOWN",
                "progress": 0.8125
              },
              {
                "timestamp": 1730747876358,
                "event": "EVALUATE",
                "tags": [],
                "annotations": [],
                "exerciseStatus": "FINISHED",
                "progress": 1
              }
            ],
            "tags": [],
            "scoring": {
              "finished": true,
              "marksTotal": 1,
              "marksEarned": 1,
              "penalties": {
                "marksPenalty": 0,
                "hintsRequested": 0,
                "mathErrors": 0
              }
            }
          }
        }
      ]
    }
  ],
  "tagDescriptions": {},
  "scoring": {
    "finished": true,
    "marksEarned": 1,
    "marksTotal": 1,
    "penalties": {
      "hintsRequested": 0,
      "mathErrors": 0,
      "marksPenalty": 0
    }
  }
}