{
  "success": true,
  "creationTimestamp": 1759927747,
  "elements": [
    {
      "id": "Q1",
      "type": "QUESTION",
      "items": [
        {
          "itemType": "TEXT",
          "content": "Bereken en vereenvoudig."
        },
        {
          "itemType": "TEXT",
          "content": "$\\frac{2}{8}+ \\frac{4}{6}$"
        },
        {
          "id": "ddXWL",
          "itemType": "INTERACTION",
          "interactionType": "MULTISTEP",
          "result": {
            "status": "CORRECT",
            "progress": 0,
            "events": [
              {
                "timestamp": 1759927766266,
                "event": "EVALUATE",
                "tags": [
                  {
                    "id": "FractionArithmeticSimplifyProper",
                    "source": "NEXT_STEP"
                  }
                ],
                "annotations": [
                  {
                    "type": "INPUT",
                    "content": "$\\frac{44}{48}$"
                  }
                ],
                "exerciseStatus": "CORRECT",
                "progress": 0.7142857142857143,
                "inputStatus": "CORRECT",
                "skillsTodo": [
                  "FractionArithmeticSimplifyProper"
                ]
              },
              {
                "timestamp": 1759927802587,
                "event": "EVALUATE",
                "tags": [
                  {
                    "id": "FractionArithmeticAddProperCommonDenominator",
                    "source": "NEXT_STEP"
                  }
                ],
                "annotations": [
                  {
                    "type": "INPUT",
                    "content": "$\\frac{12}{48}+\\frac{32}{48}$"
                  }
                ],
                "exerciseStatus": "CORRECT",
                "progress": 0,
                "inputStatus": "CORRECT",
                "skillsTodo": [
                  "FractionArithmeticAddProperCommonDenominator",
                  "FractionArithmeticSimplifyProper"
                ]
              }
            ],
            "tags": [
              {
                "id": "FractionArithmeticAddProperCommonDenominator",
                "source": "NEXT_STEP"
              }
            ],
            "scoring": {
              "marksEarned": 0,
              "marksTotal": 1,
              "penalties": {
                "marksPenalty": 0,
                "hintsRequested": 0,
                "mathErrors": 0
              },
              "finished": false
            }
          },
          "solution": "$\\frac{11}{12}$",
          "derivation": [
            {
              "expression": "$\\frac{2}{8}+ \\frac{4}{6}$"
            },
            {
              "result": "$\\frac{1}{4}+ \\frac{2}{3}$",
              "description": "Vereenvoudig de breuk"
            },
            {
              "result": "$\\frac{11}{12}$",
              "skills": [
                "FractionArithmeticAddProperUnlikeDenominator"
              ],
              "description": "Maak de breuken gelijknamig"
            }
          ]
        }
      ]
    }
  ],
  "tagDescriptions": {
    "FractionArithmeticAddProperUnlikeDenominator": {
      "descr": {
        "nl": "Ongelijknamige breuken optellen"
      },
      "stepType": "CALCULATE"
    },
    "FractionArithmeticSimplifyProper": {
      "descr": {
        "nl": "Een breuk vereenvoudigen"
      },
      "stepType": "CALCULATE"
    },
    "FractionArithmeticAddProperCommonDenominator": {
      "descr": {
        "nl": "Gelijknamige echte breuken optellen"
      },
      "stepType": "CALCULATE"
    }
  },
  "scoring": {
    "finished": false,
    "marksEarned": 0,
    "marksTotal": 1,
    "penalties": {
      "hintsRequested": 0,
      "mathErrors": 0,
      "marksPenalty": 0
    }
  }
}