{
  "success": true,
  "creationTimestamp": 1740090287,
  "elements": [
    {
      "id": "Q1",
      "type": "QUESTION",
      "items": [
        {
          "itemType": "TEXT",
          "content": "Calculate and simplify."
        },
        {
          "itemType": "TEXT",
          "content": "$\\frac{3}{6}+ \\frac{1}{5}$"
        },
        {
          "id": "ddXWL",
          "itemType": "INTERACTION",
          "interactionType": "MULTISTEP",
          "result": {
            "status": "ERROR",
            "progress": 0,
            "events": [
              {
                "timestamp": 1740090290656,
                "event": "HINT",
                "tags": [
                  {
                    "id": "FractionArithmeticSimplifyProper",
                    "weight": 100,
                    "source": "HINT"
                  }
                ],
                "annotations": [
                  {
                    "type": "HINT",
                    "content": "<h1>Simplify the fraction</h1>You can divide numerator and denominator by  $3$ .",
                    "expression": "$\\begingroup\\color{#336699}\\begingroup \\frac{3}{6}\\endgroup\\endgroup+ \\frac{1}{5}$"
                  }
                ]
              },
              {
                "timestamp": 1740090305527,
                "event": "EVALUATE",
                "tags": [
                  {
                    "id": "FractionArithmeticAddProperUnlikeDenominator",
                    "weight": -100
                  }
                ],
                "annotations": [
                  {
                    "type": "ERROR_FEEDBACK",
                    "content": "$\\frac{3}{6}+ \\frac{1}{5}$  is not equal to  $1$ .",
                    "expression": "$\\begingroup\\color{darkred}\\begingroup 1\\endgroup\\endgroup$"
                  },
                  {
                    "type": "INPUT",
                    "content": "$1$"
                  }
                ],
                "exerciseStatus": "ERROR",
                "progress": 0,
                "inputStatus": "ERROR"
              },
              {
                "timestamp": 1740090340836,
                "event": "EVALUATE",
                "tags": [
                  {
                    "id": "FractionArithmeticAddProperUnlikeDenominator",
                    "weight": -100
                  }
                ],
                "annotations": [
                  {
                    "type": "ERROR_FEEDBACK",
                    "content": "$\\frac{3}{6}+ \\frac{1}{5}$  is not equal to  $\\frac{1}{7}$ .",
                    "expression": "$\\begingroup\\color{darkred}\\begingroup \\frac{1}{7}\\endgroup\\endgroup$"
                  },
                  {
                    "type": "INPUT",
                    "content": "$\\frac{1}{7}$"
                  }
                ],
                "exerciseStatus": "ERROR",
                "progress": 0,
                "inputStatus": "ERROR"
              },
              {
                "timestamp": 1740090353815,
                "event": "EVALUATE",
                "tags": [
                  {
                    "id": "FractionArithmeticAddProperUnlikeDenominator",
                    "weight": -100
                  }
                ],
                "annotations": [
                  {
                    "type": "ERROR_FEEDBACK",
                    "content": "$\\frac{3}{6}+ \\frac{1}{5}$  is not equal to  $3$ .",
                    "expression": "$\\begingroup\\color{darkred}\\begingroup 3\\endgroup\\endgroup$"
                  },
                  {
                    "type": "INPUT",
                    "content": "$3$"
                  }
                ],
                "exerciseStatus": "ERROR",
                "progress": 0,
                "inputStatus": "ERROR"
              },
              {
                "timestamp": 1740090361523,
                "event": "EVALUATE",
                "tags": [],
                "annotations": [
                  {
                    "type": "ERROR_FEEDBACK",
                    "content": "This is not a valid mathematical expression.",
                    "expression": "$\\text{Incorrect expression}$"
                  },
                  {
                    "type": "INPUT",
                    "content": "$\\frac{1}{ }$"
                  }
                ],
                "exerciseStatus": "CORRECT",
                "progress": 0,
                "inputStatus": "PARSE_ERROR"
              },
              {
                "timestamp": 1740090370629,
                "event": "EVALUATE",
                "tags": [
                  {
                    "id": "FractionArithmeticAddProperUnlikeDenominator",
                    "weight": -100
                  }
                ],
                "annotations": [
                  {
                    "type": "ERROR_FEEDBACK",
                    "content": "$\\frac{3}{6}+ \\frac{1}{5}$  is not equal to  $\\frac{1}{10}$ .",
                    "expression": "$\\begingroup\\color{darkred}\\begingroup \\frac{1}{10}\\endgroup\\endgroup$"
                  },
                  {
                    "type": "INPUT",
                    "content": "$\\frac{1}{10}$"
                  }
                ],
                "exerciseStatus": "ERROR",
                "progress": 0,
                "inputStatus": "ERROR"
              },
              {
                "timestamp": 1740090384534,
                "event": "EVALUATE",
                "tags": [
                  {
                    "id": "FractionArithmeticAddProperUnlikeDenominator",
                    "weight": -100
                  }
                ],
                "annotations": [
                  {
                    "type": "ERROR_FEEDBACK",
                    "content": "$\\frac{3}{6}+ \\frac{1}{5}$  is not equal to  $\\frac{3}{30}$ .",
                    "expression": "$\\begingroup\\color{darkred}\\begingroup \\frac{3}{30}\\endgroup\\endgroup$"
                  },
                  {
                    "type": "INPUT",
                    "content": "$\\frac{3}{30}$"
                  }
                ],
                "exerciseStatus": "ERROR",
                "progress": 0,
                "inputStatus": "ERROR"
              },
              {
                "timestamp": 1740090386647,
                "event": "HINT",
                "tags": [
                  {
                    "id": "FractionArithmeticSimplifyProper",
                    "weight": 100,
                    "source": "HINT"
                  }
                ],
                "annotations": [
                  {
                    "type": "HINT",
                    "content": "<h1>Simplify the fraction</h1>You can divide numerator and denominator by  $3$ .",
                    "expression": "$\\begingroup\\color{#336699}\\begingroup \\frac{3}{6}\\endgroup\\endgroup+ \\frac{1}{5}$"
                  }
                ]
              }
            ],
            "tags": [
              {
                "id": "FractionArithmeticSimplifyProper",
                "weight": 100,
                "source": "HINT"
              },
              {
                "id": "FractionArithmeticAddProperUnlikeDenominator",
                "weight": -100
              },
              {
                "id": "FractionArithmeticAddProperUnlikeDenominator",
                "weight": -100
              },
              {
                "id": "FractionArithmeticAddProperUnlikeDenominator",
                "weight": -100
              },
              {
                "id": "FractionArithmeticAddProperUnlikeDenominator",
                "weight": -100
              },
              {
                "id": "FractionArithmeticAddProperUnlikeDenominator",
                "weight": -100
              },
              {
                "id": "FractionArithmeticSimplifyProper",
                "weight": 100,
                "source": "HINT"
              }
            ],
            "scoring": {
              "marksEarned": 0,
              "marksTotal": 1,
              "penalties": {
                "marksPenalty": 0,
                "hintsRequested": 2,
                "mathErrors": 5
              },
              "finished": false
            }
          },
          "solution": "$\\frac{7}{10}$",
          "derivation": [
            {
              "expression": "$\\frac{3}{6}+ \\frac{1}{5}$"
            },
            {
              "result": "$\\frac{1}{2}+ \\frac{1}{5}$",
              "skills": [
                "FractionArithmeticSimplifyProper"
              ],
              "description": "Simplify the fraction"
            },
            {
              "result": "$\\frac{7}{10}$",
              "skills": [
                "FractionArithmeticAddProperUnlikeDenominator"
              ],
              "description": "Use the same denominator for both fractions"
            }
          ]
        }
      ]
    }
  ],
  "tagDescriptions": {
    "FractionArithmeticSimplifyProper": {
      "descr": {
        "en": "Simplifying a proper fraction"
      },
      "stepType": "CALCULATE"
    },
    "FractionArithmeticAddProperUnlikeDenominator": {
      "descr": {
        "en": "Adding fractions with unlike denominators"
      },
      "stepType": "CALCULATE"
    }
  },
  "scoring": {
    "finished": false,
    "marksEarned": 0,
    "marksTotal": 1,
    "penalties": {
      "hintsRequested": 2,
      "mathErrors": 5,
      "marksPenalty": 0
    }
  }
}