{
  "success": true,
  "creationTimestamp": 1738149602,
  "elements": [
    {
      "id": "Q1",
      "type": "QUESTION",
      "items": [
        {
          "itemType": "TEXT",
          "content": "Vereenvoudig."
        },
        {
          "itemType": "TEXT",
          "content": "$\\text{-}8 t \\cdot \\text{-}8 a $"
        },
        {
          "id": "I1",
          "itemType": "INTERACTION",
          "interactionType": "MULTISTEP",
          "result": {
            "status": "FINISHED",
            "progress": 1,
            "events": [
              {
                "timestamp": 1738224049094,
                "event": "EVALUATE",
                "tags": [],
                "annotations": [
                  {
                    "type": "INPUT",
                    "content": "$64ta$"
                  }
                ],
                "exerciseStatus": "FINISHED",
                "progress": 1,
                "inputStatus": "FINISHED"
              }
            ],
            "tags": [],
            "scoring": {
              "marksEarned": 1,
              "marksTotal": 1,
              "penalties": {
                "marksPenalty": 0,
                "hintsRequested": 0,
                "mathErrors": 0
              },
              "finished": true
            }
          },
          "solution": "$64 a  t $",
          "derivation": [
            {
              "expression": "$\\text{-}8\\cdot \\text{-}8 a  t $"
            },
            {
              "result": "$64 a  t $",
              "description": "Reken uit:  $\\text{-}8\\cdot \\text{-}8$"
            }
          ]
        }
      ]
    }
  ],
  "tagDescriptions": {},
  "scoring": {
    "finished": true,
    "marksEarned": 1,
    "marksTotal": 1,
    "penalties": {
      "hintsRequested": 0,
      "mathErrors": 0,
      "marksPenalty": 0
    }
  }
}