{
  "success": true,
  "creationTimestamp": 1733690326,
  "elements": [
    {
      "id": "Q1",
      "type": "QUESTION",
      "items": [
        {
          "itemType": "TEXT",
          "content": "Schrijf zo kort mogelijk."
        },
        {
          "itemType": "TEXT",
          "content": "$\\text{-}\\sqrt{70}+ \\sqrt{61}+ \\sqrt{70}+ \\sqrt{61}- \\sqrt{61}$"
        },
        {
          "id": "WbEOf",
          "itemType": "INTERACTION",
          "interactionType": "MULTISTEP",
          "result": {
            "status": "ERROR",
            "progress": 0,
            "events": [
              {
                "timestamp": 1733690360151,
                "event": "EVALUATE",
                "tags": [],
                "annotations": [
                  {
                    "type": "ERROR_FEEDBACK",
                    "content": "hier zit een fout.",
                    "expression": "$\\begingroup\\color{darkred}\\begingroup \\text{-}2 \\sqrt{70}\\endgroup\\endgroup+ \\sqrt{61}$"
                  },
                  {
                    "type": "INPUT",
                    "content": "$-2\\sqrt{70}+\\sqrt{61}$"
                  }
                ],
                "exerciseStatus": "ERROR",
                "progress": 0,
                "inputStatus": "ERROR"
              },
              {
                "timestamp": 1733690398702,
                "event": "EVALUATE",
                "tags": [],
                "annotations": [
                  {
                    "type": "ERROR_FEEDBACK",
                    "content": "<h1>$\\text{-}\\sqrt{70}+ \\sqrt{61}+ \\sqrt{70}+ \\sqrt{61}- \\sqrt{61}$  is niet gelijk aan  $\\sqrt{70}+ \\sqrt{61}$ .</h1>Je bent vergeten  $\\sqrt{61}- \\sqrt{70}- \\sqrt{61}$  op te tellen.",
                    "expression": "$\\begingroup\\color{darkred}\\begingroup \\sqrt{70}+ \\sqrt{61}\\endgroup\\endgroup$"
                  },
                  {
                    "type": "INPUT",
                    "content": "$\\sqrt{70}+\\sqrt{61}$"
                  }
                ],
                "exerciseStatus": "ERROR",
                "progress": 0,
                "inputStatus": "ERROR"
              }
            ],
            "tags": [],
            "scoring": {
              "marksEarned": 0,
              "marksTotal": 1,
              "penalties": {
                "marksPenalty": 0,
                "hintsRequested": 0,
                "mathErrors": 2
              },
              "finished": false
            }
          },
          "solution": "$\\sqrt{61}$",
          "derivation": [
            {
              "expression": "$\\text{-}\\sqrt{70}+ \\sqrt{61}+ \\sqrt{70}+ \\sqrt{61}- \\sqrt{61}$"
            },
            {
              "result": "$\\sqrt{61}$",
              "description": "Neem de gelijksoortige termen samen"
            }
          ]
        }
      ]
    }
  ],
  "tagDescriptions": {},
  "scoring": {
    "finished": false,
    "marksEarned": 0,
    "marksTotal": 1,
    "penalties": {
      "hintsRequested": 0,
      "mathErrors": 2,
      "marksPenalty": 0
    }
  }
}