{
  "success": true,
  "creationTimestamp": 1755522838,
  "elements": [
    {
      "id": "Q1",
      "type": "QUESTION",
      "items": [
        {
          "itemType": "TEXT",
          "content": "Calculate and simplify."
        },
        {
          "itemType": "TEXT",
          "content": "$4\\times \\frac{2}{3}$"
        },
        {
          "id": "roPhK",
          "itemType": "INTERACTION",
          "interactionType": "MULTISTEP",
          "result": {
            "status": "FINISHED",
            "progress": 1,
            "events": [
              {
                "timestamp": 1755522857947,
                "event": "EVALUATE",
                "tags": [
                  {
                    "id": "FractionArithmeticSimilarImproperToMixed",
                    "source": "FINISHED_STEP"
                  }
                ],
                "annotations": [
                  {
                    "type": "INPUT",
                    "content": "$2\\frac{2}{3}$"
                  }
                ],
                "exerciseStatus": "FINISHED",
                "progress": 1,
                "inputStatus": "FINISHED"
              }
            ],
            "tags": [
              {
                "id": "FractionArithmeticSimilarImproperToMixed",
                "source": "FINISHED_STEP"
              }
            ],
            "scoring": {
              "marksEarned": 1,
              "marksTotal": 1,
              "penalties": {
                "marksPenalty": 0,
                "hintsRequested": 0,
                "mathErrors": 0
              },
              "finished": true
            }
          },
          "solution": "$2\\frac{2}{3}$",
          "derivation": [
            {
              "expression": "$4\\times \\frac{2}{3}$"
            },
            {
              "result": "$\\frac{8}{3}$",
              "description": "Rewrite."
            },
            {
              "result": "$2\\frac{2}{3}$",
              "skills": [
                "FractionArithmeticSimilarMixedToImproper"
              ],
              "description": "Rewrite the improper fraction into a mixed fraction"
            }
          ]
        }
      ]
    }
  ],
  "tagDescriptions": {
    "FractionArithmeticSimilarMixedToImproper": {
      "descr": {
        "en": "Writing a mixed fraction into a similar improper fraction"
      },
      "stepType": "CALCULATE"
    },
    "FractionArithmeticSimilarImproperToMixed": {
      "descr": {
        "en": "Writing an improper fraction into a similar mixed fraction"
      },
      "stepType": "CALCULATE"
    }
  },
  "scoring": {
    "finished": true,
    "marksEarned": 1,
    "marksTotal": 1,
    "penalties": {
      "hintsRequested": 0,
      "mathErrors": 0,
      "marksPenalty": 0
    }
  }
}