{
  "success": true,
  "creationTimestamp": 1750357485,
  "elements": [
    {
      "id": "Q1",
      "type": "QUESTION",
      "items": [
        {
          "itemType": "TEXT",
          "content": "Factorise."
        },
        {
          "itemType": "TEXT",
          "content": "$32+ 40 p $"
        },
        {
          "id": "eZx3R",
          "itemType": "INTERACTION",
          "interactionType": "MULTISTEP",
          "result": {
            "status": "CORRECT",
            "progress": 0,
            "events": [
              {
                "timestamp": 1750357518919,
                "event": "EVALUATE",
                "tags": [],
                "annotations": [
                  {
                    "type": "INPUT",
                    "content": "$4\\ \\left(\\ 8\\ +\\ 10p\\ \\right)$"
                  }
                ],
                "exerciseStatus": "CORRECT",
                "progress": 0,
                "inputStatus": "CORRECT",
                "skillsTodo": [
                  "FactorSingleBrackets"
                ]
              },
              {
                "timestamp": 1750357536593,
                "event": "EVALUATE",
                "tags": [],
                "annotations": [
                  {
                    "type": "ERROR_FEEDBACK",
                    "content": "This is not a valid mathematical expression.",
                    "expression": "$\\text{Incorrect expression}$"
                  },
                  {
                    "type": "INPUT",
                    "content": "$4\\ 8\\ +\\ 10p$"
                  }
                ],
                "exerciseStatus": "CORRECT",
                "progress": 0,
                "inputStatus": "PARSE_ERROR"
              },
              {
                "timestamp": 1750357539690,
                "event": "HINT",
                "tags": [
                  {
                    "id": "FactorSingleBrackets",
                    "weight": 100,
                    "source": "HINT"
                  }
                ],
                "annotations": [
                  {
                    "type": "HINT",
                    "content": "<h1>Factorise</h1>The terms have a common constant factor  $2$",
                    "expression": "$4 \\left(\\begingroup\\color{#336699}\\begingroup 8+ 10 p \\endgroup\\endgroup\\right)$"
                  }
                ]
              },
              {
                "timestamp": 1750357565348,
                "event": "EVALUATE",
                "tags": [],
                "annotations": [
                  {
                    "type": "INPUT",
                    "content": "$4\\ \\left(\\ 8\\ +\\ 10p\\ \\right)\\ =\\ 32+40p$"
                  }
                ],
                "exerciseStatus": "CORRECT",
                "progress": 0,
                "inputStatus": "CORRECT",
                "skillsTodo": [
                  "FactorSingleBrackets"
                ]
              }
            ],
            "tags": [
              {
                "id": "FactorSingleBrackets",
                "weight": 100,
                "source": "HINT"
              }
            ],
            "scoring": {
              "marksEarned": 0,
              "marksTotal": 1,
              "penalties": {
                "marksPenalty": 0,
                "hintsRequested": 1,
                "mathErrors": 0
              },
              "finished": false
            }
          },
          "solution": "$8 \\left(5 p + 4\\right)$",
          "derivation": [
            {
              "expression": "$32+ 40 p $"
            },
            {
              "result": "$8 \\left(5 p + 4\\right)$",
              "skills": [
                "FactorSingleBrackets"
              ],
              "description": "Factorise"
            }
          ]
        }
      ]
    }
  ],
  "tagDescriptions": {
    "FactorSingleBrackets": {
      "descr": {
        "en": "Factoring a common factor"
      },
      "stepType": "ALGEBRA"
    }
  },
  "scoring": {
    "finished": false,
    "marksEarned": 0,
    "marksTotal": 1,
    "penalties": {
      "hintsRequested": 1,
      "mathErrors": 0,
      "marksPenalty": 0
    }
  }
}